{"class_prob_max": 0.4608, "class_prob_mean": 0.3333333333333333, "class_prob_median": 0.4608, "class_prob_min": 0.0784, "class_prob_std": 0.2207787429381129, "corr_with_dependent_abs_25p": null, "corr_with_dependent_abs_75p": null, "corr_with_dependent_abs_kurtosis": null, "corr_with_dependent_abs_max": null, "corr_with_dependent_abs_mean": null, "corr_with_dependent_abs_median": null, "corr_with_dependent_abs_min": null, "corr_with_dependent_abs_skew": null, "corr_with_dependent_abs_std": null, "dataset_hash": "61078fbd1af51c5bf8df3446b4e2d9db1c363c61397ee147b9b02935c6387e1e", "diversity_fraction": 0.8311344295511353, "entropy_dependent": 0.9136485598712406, "kurtosis_kurtosis": -3.0, "kurtosis_max": -1.3007984392499732, "kurtosis_mean": -1.3007984392499732, "kurtosis_median": -1.3007984392499732, "kurtosis_min": -1.3007984392499732, "kurtosis_skew": 0.0, "kurtosis_std": 0.0, "metafeature_version": "1.0", "n_categorical": 0, "n_classes": 3, "n_columns": 5, "n_numerical": 4, "n_rows": 625, "pca_fraction_95": 1.0, "ratio_rowcol": 125.0, "skew_kurtosis": -3.0, "skew_max": 0.0, "skew_mean": 0.0, "skew_median": 0.0, "skew_min": 0.0, "skew_skew": 0.0, "skew_std": 0.0, "symbols_kurtosis": 0, "symbols_max": 0, "symbols_mean": 0, "symbols_min": 0, "symbols_skew": 0, "symbols_std": 0, "symbols_sum": 0}